{
    "pokedex-no": 718,
    "type": {
        "type-0": "Dragon",
        "type-1": "Ground"
    },
    "abilities": {
        "ability-0": "Aura Break",
        "ability-1": "Power Construct"
    },
    "stats": {
        "HP": {
            "base": 108,
            "min": 326,
            "max": 420
        },
        "Attack": {
            "base": 100,
            "min": 184,
            "max": 328
        },
        "Defense": {
            "base": 121,
            "min": 222,
            "max": 375
        },
        "Sp. Atk": {
            "base": 81,
            "min": 150,
            "max": 287
        },
        "Sp. Def": {
            "base": 95,
            "min": 175,
            "max": 317
        },
        "Speed": {
            "base": 95,
            "min": 175,
            "max": 317
        }
    }
}