{
    "pokedex-no": 629,
    "type": {
        "type-0": "Dark",
        "type-1": "Flying"
    },
    "abilities": {
        "ability-0": "Big Pecks",
        "ability-1": "Overcoat",
        "ability-2": "Weak Armor"
    },
    "stats": {
        "HP": {
            "base": 70,
            "min": 250,
            "max": 344
        },
        "Attack": {
            "base": 55,
            "min": 103,
            "max": 229
        },
        "Defense": {
            "base": 75,
            "min": 139,
            "max": 273
        },
        "Sp. Atk": {
            "base": 45,
            "min": 85,
            "max": 207
        },
        "Sp. Def": {
            "base": 65,
            "min": 121,
            "max": 251
        },
        "Speed": {
            "base": 60,
            "min": 112,
            "max": 240
        }
    }
}