{
    "pokedex-no": 223,
    "type": {
        "type-0": "Water"
    },
    "abilities": {
        "ability-0": "Hustle",
        "ability-1": "Sniper",
        "ability-2": "Moody"
    },
    "stats": {
        "HP": {
            "base": 35,
            "min": 180,
            "max": 274
        },
        "Attack": {
            "base": 65,
            "min": 121,
            "max": 251
        },
        "Defense": {
            "base": 35,
            "min": 67,
            "max": 185
        },
        "Sp. Atk": {
            "base": 65,
            "min": 121,
            "max": 251
        },
        "Sp. Def": {
            "base": 35,
            "min": 67,
            "max": 185
        },
        "Speed": {
            "base": 65,
            "min": 121,
            "max": 251
        }
    }
}