{
    "pokedex-no": 15,
    "type": {
        "type-0": "Bug",
        "type-1": "Poison"
    },
    "abilities": {
        "ability-0": "Adaptability"
    },
    "stats": {
        "HP": {
            "base": 65,
            "min": 240,
            "max": 334
        },
        "Attack": {
            "base": 150,
            "min": 274,
            "max": 438
        },
        "Defense": {
            "base": 40,
            "min": 76,
            "max": 196
        },
        "Sp. Atk": {
            "base": 15,
            "min": 31,
            "max": 141
        },
        "Sp. Def": {
            "base": 80,
            "min": 148,
            "max": 284
        },
        "Speed": {
            "base": 145,
            "min": 265,
            "max": 427
        }
    }
}