{
    "pokedex-no": 857,
    "type": {
        "type-0": "Psychic"
    },
    "abilities": {
        "ability-0": "Healer",
        "ability-1": "Anticipation",
        "ability-2": "Magic Bounce"
    },
    "stats": {
        "HP": {
            "base": 57,
            "min": 224,
            "max": 318
        },
        "Attack": {
            "base": 40,
            "min": 76,
            "max": 196
        },
        "Defense": {
            "base": 65,
            "min": 121,
            "max": 251
        },
        "Sp. Atk": {
            "base": 86,
            "min": 159,
            "max": 298
        },
        "Sp. Def": {
            "base": 73,
            "min": 135,
            "max": 269
        },
        "Speed": {
            "base": 49,
            "min": 92,
            "max": 216
        }
    }
}